zcode/__init__.py
zcode/compression.py
zcode/decompression.py
zcode/main.py
zcode-0.0.1.dist-info/LICENSE
zcode-0.0.1.dist-info/METADATA
zcode-0.0.1.dist-info/WHEEL
zcode-0.0.1.dist-info/entry_points.txt
zcode-0.0.1.dist-info/top_level.txt
zcode-0.0.1.dist-info/RECORD
