Metadata-Version: 2.1
Name: zcode
Version: 0.0.1
Summary: Compress and decompress to and from `.zee` files!
Home-page: https://github.com/vahidzee/zcode
Author: Vahid Zehtab
Author-email: vahid98zee@gmail.com
License: MIT
Keywords: zcode,compression,lzw,lossless-compression
Platform: UNKNOWN
Classifier: Development Status :: 3 - Alpha
Classifier: Intended Audience :: Developers
Classifier: Intended Audience :: End Users/Desktop
Classifier: Intended Audience :: Education
Classifier: Topic :: System :: Archiving :: Compression
Classifier: License :: OSI Approved :: MIT License
Classifier: Programming Language :: Python :: 3.8
